asmc/__init__.py
asmc-1.3.dist-info/COPYING
asmc-1.3.dist-info/LICENSE
asmc-1.3.dist-info/METADATA
asmc-1.3.dist-info/WHEEL
asmc-1.3.dist-info/top_level.txt
asmc-1.3.dist-info/RECORD
