Metadata-Version: 2.1
Name: asmc
Version: 1.3
Summary: The Ascertained Sequentially Markovian Coalescent and related tools
Home-page: https://github.com/PalamaraLab/
Author: PalamaraLab
Classifier: Programming Language :: Python :: 3
Classifier: License :: OSI Approved :: GNU General Public License v3 (GPLv3)
Requires-Python: >=3.6
License-File: LICENSE
License-File: COPYING
Requires-Dist: asmc-asmc (==1.3)
Requires-Dist: asmc-preparedecoding (==2.2.3)
Provides-Extra: pypi
Requires-Dist: build ; extra == 'pypi'
Requires-Dist: twine ; extra == 'pypi'
